rankcomp/__init__.py
rankcomp/feature_selection.py
rankcomp/get_reverse_index.py
rankcomp/load_data.py
rankcomp/main1.py
rankcomp/main2.py
rankcomp/p_selection.py
rankcomp/setup.py
rankcomp/test_ml_model.py
rankcomp/utils.py
rankcomp-0.0.2.dist-info/LICENSE
rankcomp-0.0.2.dist-info/METADATA
rankcomp-0.0.2.dist-info/WHEEL
rankcomp-0.0.2.dist-info/top_level.txt
rankcomp-0.0.2.dist-info/RECORD
